BenBot/__init__.py
BenBot-0.0.4.dist-info/LICENSE
BenBot-0.0.4.dist-info/METADATA
BenBot-0.0.4.dist-info/WHEEL
BenBot-0.0.4.dist-info/top_level.txt
BenBot-0.0.4.dist-info/RECORD
