Metadata-Version: 2.1
Name: BenBot
Version: 0.0.4
Summary: Python wrapper for BenBot API.
Home-page: https://github.com/xMistt/BenBot
Author: xMistt
License: UNKNOWN
Platform: UNKNOWN
Classifier: Programming Language :: Python :: 3
Classifier: License :: OSI Approved :: MIT License
Classifier: Operating System :: OS Independent
Requires-Dist: requests
